[
  {
    "id": "TER-001",
    "nom": "Désertique",
    "description": "L'immensité aride favorise l'espionnage et l'isolation, mais asphyxie les flux financiers.",
    "modificateurs": {
      "Economique": -1,
      "Renseignement": 1,
      "Isolationniste": 1,
      "Militaire": 0,
      "Diplomatique": 0
    }
  },
  {
    "id": "TER-002",
    "nom": "Glacial",
    "description": "Le froid extrême fige les armées et l'économie, poussant les États à se replier sur eux-mêmes.",
    "modificateurs": {
      "Economique": -1,
      "Renseignement": 0,
      "Isolationniste": 1,
      "Militaire": -1,
      "Diplomatique": 0
    }
  },
  {
    "id": "TER-003",
    "nom": "Tropical",
    "description": "La jungle dense est un enfer tactique idéal pour les militaires, mais un cauchemar pour le renseignement classique.",
    "modificateurs": {
      "Economique": 0,
      "Renseignement": -1,
      "Isolationniste": 0,
      "Militaire": 1,
      "Diplomatique": 1
    }
  },
  {
    "id": "TER-004",
    "nom": "Tempéré",
    "description": "Climat standard. Aucune influence majeure sur les doctrines politiques ou militaires.",
    "modificateurs": {
      "Economique": 0,
      "Renseignement": 0,
      "Isolationniste": 0,
      "Militaire": 0,
      "Diplomatique": 0
    }
  },
  {
    "id": "TER-005",
    "nom": "Océanique",
    "description": "La domination des mers booste l'économie et la projection militaire, au détriment de l'isolationnisme.",
    "modificateurs": {
      "Economique": 1,
      "Renseignement": 0,
      "Isolationniste": -1,
      "Militaire": 1,
      "Diplomatique": 0
    }
  },
  {
    "id": "TER-006",
    "nom": "Montagneux",
    "description": "Les sommets favorisent la défense et les rencontres diplomatiques discrètes, mais ralentissent les opérations de terrain.",
    "modificateurs": {
      "Economique": 0,
      "Renseignement": 1,
      "Isolationniste": 0,
      "Militaire": -1,
      "Diplomatique": 1
    }
  }
]
